pyproject.toml
setup.cfg
setup.py
my_open_weather/__init__.py
my_open_weather/client.py
my_open_weather.egg-info/PKG-INFO
my_open_weather.egg-info/SOURCES.txt
my_open_weather.egg-info/dependency_links.txt
my_open_weather.egg-info/not-zip-safe
my_open_weather.egg-info/top_level.txt