Metadata-Version: 2.4
Name: my_open_weather
Version: 0.0
Summary: weather
Author-email: 21qquestions@gmail.com
Dynamic: author-email
Dynamic: summary
